karabo_bridge/__init__.py
karabo_bridge/client.py
karabo_bridge/qt.py
karabo_bridge/serializer.py
karabo_bridge/server.py
karabo_bridge/simulation.py
karabo_bridge/cli/__init__.py
karabo_bridge/cli/glimpse.py
karabo_bridge/cli/monitor.py
karabo_bridge/cli/simulation.py
karabo_bridge/tests/__init__.py
karabo_bridge/tests/conftest.py
karabo_bridge/tests/test_client.py
karabo_bridge/tests/test_glimpse.py
karabo_bridge/tests/test_monitor.py
karabo_bridge/tests/test_qt.py
karabo_bridge/tests/test_serialize.py
karabo_bridge/tests/test_server.py
karabo_bridge/tests/test_simulation.py
karabo_bridge/tests/utils.py
karabo_bridge-0.7.0.dist-info/LICENSE
karabo_bridge-0.7.0.dist-info/METADATA
karabo_bridge-0.7.0.dist-info/WHEEL
karabo_bridge-0.7.0.dist-info/entry_points.txt
karabo_bridge-0.7.0.dist-info/top_level.txt
karabo_bridge-0.7.0.dist-info/RECORD
