Metadata-Version: 2.1
Name: karabo-bridge
Version: 0.7.0
Summary: Python 3 tools to request data from the Karabo controlsystem.
Home-page: https://github.com/European-XFEL/karabo-bridge-py
Author: European XFEL GmbH
Author-email: da-support@xfel.eu
Maintainer: Thomas Michelat
License: BSD-3-Clause
Classifier: Intended Audience :: Developers
Classifier: Intended Audience :: Science/Research
Classifier: License :: OSI Approved :: BSD License
Requires-Python: >=3.7
License-File: LICENSE
Requires-Dist: msgpack (>=0.5.4)
Requires-Dist: msgpack-numpy
Requires-Dist: numpy
Requires-Dist: pyzmq (>=17.0.0)
Provides-Extra: qt
Requires-Dist: QtPy ; extra == 'qt'
Provides-Extra: test
Requires-Dist: pytest ; extra == 'test'
Requires-Dist: pytest-cov ; extra == 'test'
Requires-Dist: pytest-qt ; extra == 'test'
Requires-Dist: h5py ; extra == 'test'
Requires-Dist: testpath ; extra == 'test'
Requires-Dist: QtPy ; extra == 'test'
Requires-Dist: PyQt5 ; extra == 'test'
